HISTORY.rst
LICENSE
MANIFEST.in
README.rst
setup.cfg
setup.py
python_yo.egg-info/PKG-INFO
python_yo.egg-info/SOURCES.txt
python_yo.egg-info/dependency_links.txt
python_yo.egg-info/not-zip-safe
python_yo.egg-info/top_level.txt
tests/__init__.py
tests/test_yo.py
yo/__init__.py
yo/config.py
yo/yo.py
yo/http_client/__init__.py
yo/http_client/http_client.py