Metadata-Version: 1.1
Name: python-yo
Version: 0.1.0
Summary: A Python client for the Yo platform
Home-page: https://github.com/mcos/yo-py
Author: Mark Costello
Author-email: mark@markcostello.net
License: BSD
Keywords: yo
Platform: UNKNOWN
Classifier: Development Status :: 2 - Pre-Alpha
Classifier: Intended Audience :: Developers
Classifier: License :: OSI Approved :: BSD License
Classifier: Natural Language :: English
Classifier: Programming Language :: Python :: 2
Classifier: Programming Language :: Python :: 2.6
Classifier: Programming Language :: Python :: 2.7
Classifier: Programming Language :: Python :: 3
Classifier: Programming Language :: Python :: 3.3
Classifier: Programming Language :: Python :: 3.4
